callusgs/__init__.py
callusgs/api.py
callusgs/cli.py
callusgs/cli_funcs.py
callusgs/errors.py
callusgs/exits.py
callusgs/storage.py
callusgs/types.py
callusgs/utils.py
callusgs-0.3.0.dist-info/LICENSE
callusgs-0.3.0.dist-info/METADATA
callusgs-0.3.0.dist-info/WHEEL
callusgs-0.3.0.dist-info/entry_points.txt
callusgs-0.3.0.dist-info/RECORD
