Metadata-Version: 2.1
Name: callusgs
Version: 0.3.0
Summary: Implementation of USGS's machine-to-machine API (v1.5.0)
Home-page: https://github.com/Florian-Katerndahl/callusgs
License: GPL-2.0-only
Keywords: USGS,API,machine-to-machine,Landsat,CLI,geodata,GIS,EROS,download,EarthExplorer
Author: Florian-Katerndahl
Author-email: florian@katerndahl.com
Requires-Python: >=3.9,<4.0
Classifier: Environment :: Console
Classifier: Framework :: Sphinx
Classifier: Intended Audience :: Developers
Classifier: Intended Audience :: Science/Research
Classifier: License :: OSI Approved :: GNU General Public License v2 (GPLv2)
Classifier: Natural Language :: English
Classifier: Operating System :: OS Independent
Classifier: Programming Language :: Python :: 3
Classifier: Programming Language :: Python :: 3.9
Classifier: Programming Language :: Python :: 3.10
Classifier: Programming Language :: Python :: 3.11
Classifier: Programming Language :: Python :: 3.12
Classifier: Programming Language :: Python :: 3 :: Only
Classifier: Topic :: Scientific/Engineering :: Atmospheric Science
Classifier: Topic :: Scientific/Engineering :: GIS
Classifier: Typing :: Typed
Requires-Dist: fiona (>=1.9.6,<2.0.0)
Requires-Dist: requests (>=2.32.3,<3.0.0)
Requires-Dist: tqdm (>=4.66.4,<5.0.0)
Project-URL: Bug Tracker, https://github.com/Florian-Katerndahl/callusgs/issues
Project-URL: Documentation, https://callusgs.readthedocs.io/
Project-URL: Repository, https://github.com/Florian-Katerndahl/callusgs
